Workbook

Sheet Summary
A1: How much do we need?
A2: Active scenario is set on the Assumptions sheet.
A4: REQUIREMENT BY RUNWAY LENGTH | B4: 12 months | C4: 24 months | D4: 36 months | E4: Note
A5: Founder stipends | B5: =Assumptions!$B$17*Assumptions!$B$18*12 -> 18000 | C5: =Assumptions!$B$17*Assumptions!$B$18*24 -> 36000 | D5: =Assumptions!$B$17*Assumptions!$B$18*36 -> 54000
A6: Infrastructure & tools | B6: ='Operating Costs'!$B$13*Assumptions!$B$20*12 -> 3600 | C6: ='Operating Costs'!$B$13*Assumptions!$B$20*24 -> 7200 | D6: ='Operating Costs'!$B$13*Assumptions!$B$20*36 -> 10800
A7: One-off & periodic | B7: ='One-off Costs'!$C$14*12/36 -> 3653.3333 | C7: ='One-off Costs'!$C$14*24/36 -> 7306.6667 | D7: ='One-off Costs'!$C$14*36/36 -> 10960
A8: Subtotal | B8: =SUM(B5:B7) -> 25253.333 | C8: =SUM(C5:C7) -> 50506.667 | D8: =SUM(D5:D7) -> 75760
A9: Contingency buffer | B9: =B8*Assumptions!$B$22 -> 3788 | C9: =C8*Assumptions!$B$22 -> 7576 | D9: =D8*Assumptions!$B$22 -> 11364
A10: TOTAL REQUIREMENT | B10: =B8+B9 -> 29041.333 | C10: =C8+C9 -> 58082.667 | D10: =D8+D9 -> 87124 | E10: This is the number to put on the ask slide.
A12: Monthly burn rate | B12: =Assumptions!$B$17*Assumptions!$B$18+'Operating Costs'!$B$13*Assumptions!$B$20 -> 1800 | E12: Excludes one-off items.
A13: Months of runway from $10,000 | B13: =IFERROR(10000/B12,0) -> 5.5555556 | E13: What the current offer on the table actually buys.
A14: Months of runway from $30,000 | B14: =IFERROR(30000/B12,0) -> 16.666667
A15: Months of runway from $40,000 (IT Park grant) | B15: =IFERROR(40000/B12,0) -> 22.222222
A17: ALL THREE SCENARIOS AT 36 MONTHS
B18: Lean | C18: Base | D18: Full
A19: Total 36-month requirement | B19: =(Assumptions!B6*Assumptions!B7*36+'Operating Costs'!$B$13*Assumptions!B9*36+'One-off Costs'!$B$14*Assumptions!B10)*(1+Assumptions!B11) -> 62466.8 | C19: =(Assumptions!C6*Assumptions!C7*36+'Operating Costs'!$B$13*Assumptions!C9*36+'One-off Costs'!$B$14*Assumptions!C10)*(1+Assumptions!C11) -> 87124 | D19: =(Assumptions!D6*Assumptions!D7*36+'Operating Costs'!$B$13*Assumptions!D9*36+'One-off Costs'!$B$14*Assumptions!D10)*(1+Assumptions!D11) -> 155131.2 | E19: Independent of the active-scenario selector.

Sheet Assumptions
A1: SAFRON — Funding Requirement Model
A2: All blue cells are inputs. Change them and every sheet recalculates.
A3: Currency: USD. Base date: August 2026.
A5: SCENARIO LEVERS | B5: Lean | C5: Base | D5: Full | E5: Basis / source
A6: Monthly stipend per funded founder | B6: 600 | C6: 750 | D6: 900 | E6: User-stated need: $600-900/mo. Tashkent IT market avg ~$1,450/mo (Flexa 2026) — we pay below market.
A7: Number of funded founders | B7: 2 | C7: 2 | D7: 3 | E7: You + developer. PM leaves for UK study in Sept 2026 (unpaid advisor). Full case adds 1 contractor.
A8: Runway (months) | B8: 36 | C8: 36 | D8: 36 | E8: Seasonality: missing an Uzbek tourism season costs a full year. 3 yrs = 3 shots at the season.
A9: Infra & tools multiplier | B9: 0.7 | C9: 1 | D9: 1.6 | E9: Applied to the Operating Costs sheet. Lean = free tiers, Full = higher AI spend.
A10: One-off cost multiplier | B10: 0.55 | C10: 1 | D10: 1.35 | E10: Applied to the One-off Costs sheet.
A11: Contingency buffer % | B11: 0.1 | C11: 0.15 | D11: 0.2 | E11: Standard project buffer. Investors expect to see one.
A13: ACTIVE SCENARIO (type Lean, Base or Full) | B13: Base | E13: Drives the Summary sheet. Column index below resolves it.
A14: Column index | B14: =MATCH(B13,{"Lean","Base","Full"},0) -> 2
A16: RESOLVED ACTIVE VALUES
A17: Stipend per founder | B17: =INDEX(B6:D6,$B$14) -> 750
A18: Funded founders | B18: =INDEX(B7:D7,$B$14) -> 2
A19: Runway (months) | B19: =INDEX(B8:D8,$B$14) -> 36
A20: Infra multiplier | B20: =INDEX(B9:D9,$B$14) -> 1
A21: One-off multiplier | B21: =INDEX(B10:D10,$B$14) -> 1
A22: Buffer % | B22: =INDEX(B11:D11,$B$14) -> 0.15

Sheet Operating Costs
A1: Recurring monthly costs (before scenario multiplier)
A3: Item | B3: $ / month | C3: 36-mo total | D3: Basis
A4: Supabase Pro | B4: 25 | C4: =B4*Assumptions!$B$19*Assumptions!$B$20 -> 900 | D4: Managed Postgres. Free tier insufficient past pilot (PRD §7.2 targets 10k concurrent users).
A5: Vercel Pro | B5: 20 | C5: =B5*Assumptions!$B$19*Assumptions!$B$20 -> 720 | D5: Hosting for 4 Next.js apps. Team seat.
A6: Mapbox (beyond free tier) | B6: 30 | C6: =B6*Assumptions!$B$19*Assumptions!$B$20 -> 1080 | D6: Free tier = 50k loads/mo (TECHNICAL_PLAN §10.2). Paid once Survival Map ships.
A7: AI APIs — OpenAI / Claude / Kimi | B7: 100 | C7: =B7*Assumptions!$B$19*Assumptions!$B$20 -> 3600 | D7: TECHNICAL_PLAN §10.2 estimates $50-200/mo at MVP. Menu scanner + translator + itinerary AI.
A8: AI coding subscriptions (2 seats) | B8: 60 | C8: =B8*Assumptions!$B$19*Assumptions!$B$20 -> 2160 | D8: Developer productivity tooling. ~$30/seat.
A9: Domain, DNS, Cloudflare, email | B9: 15 | C9: =B9*Assumptions!$B$19*Assumptions!$B$20 -> 540 | D9: uzbektourism.app + safron domains, WAF, transactional email.
A10: Error monitoring & logging | B10: 15 | C10: =B10*Assumptions!$B$19*Assumptions!$B$20 -> 540 | D10: Sentry or equivalent. Required before public launch.
A11: Design tooling | B11: 15 | C11: =B11*Assumptions!$B$19*Assumptions!$B$20 -> 540 | D11: Figma seat.
A12: Misc SaaS / contingency | B12: 20 | C12: =B12*Assumptions!$B$19*Assumptions!$B$20 -> 720 | D12: Unallocated small tools.
A13: TOTAL / month | B13: =SUM(B4:B12) -> 300 | C13: =SUM(C4:C12) -> 10800

Sheet One-off Costs
A1: One-off and periodic costs across the full runway
A3: Item | B3: Raw $ | C3: Scenario-adj $ | D3: Basis
A4: Company registration & setup | B4: 500 | C4: =B4*Assumptions!$B$21 -> 500 | D4: LLC formation. Needed before any investment or government contract.
A5: Accounting (36 mo) | B5: 2160 | C5: =B5*Assumptions!$B$21 -> 2160 | D5: ~$60/mo bookkeeping. Mandatory once you have revenue and an investor.
A6: Pilot field work — Navoi / Nurata travel | B6: 900 | C6: =B6*Assumptions!$B$21 -> 900 | D6: Deck slide 18: on-site provider onboarding. ~6 trips.
A7: Provider onboarding kit & materials | B7: 400 | C7: =B7*Assumptions!$B$21 -> 400 | D7: Printed guides in Uzbek for low-literacy providers.
A8: QR standees — airports, hotels | B8: 600 | C8: =B8*Assumptions!$B$21 -> 600 | D8: PRD §9.1: QR distribution is the core acquisition assumption.
A9: Security audit (pre-launch) | B9: 1500 | C9: =B9*Assumptions!$B$21 -> 1500 | D9: Deck slide 18 month 4-6. Required before handling passport data.
A10: Legal — ToS, privacy policy, contracts | B10: 1200 | C10: =B10*Assumptions!$B$21 -> 1200 | D10: GDPR-aligned policies promised in PRD §7.3 and deck slide 16.
A11: Hardware — laptop replacement, test devices | B11: 1400 | C11: =B11*Assumptions!$B$21 -> 1400 | D11: Low-end Android needed to test the Provider PWA on real target hardware.
A12: Launch marketing | B12: 1500 | C12: =B12*Assumptions!$B$21 -> 1500 | D12: Deck slide 18 months 10-12.
A13: Grant / accelerator application costs | B13: 800 | C13: =B13*Assumptions!$B$21 -> 800 | D13: IT Park, ADB, EBRD applications and related travel.
A14: TOTAL | B14: =SUM(B4:B13) -> 10960 | C14: =SUM(C4:C13) -> 10960
