Workbook

Sheet Snapshot
A1: SAFRON — Revenue & Return, at the assumptions as supplied
A2: Static snapshot for reading. The Assumptions, Revenue and P&L sheets are live — change a blue cell there and they recalculate.
A3: Base: 500,000 tourists/yr, 90% in main season, adoption 5% / 30% / 50%.
A5: MARKET | B5: Year 1 | C5: Year 2 | D5: Year 3
A6: App users | B6: 22500 | C6: 135000 | D6: 225000 | E6: 500,000 x 90% x adoption
A7: REVENUE
A8: Tourist booking commission | B8: 6480 | C8: 72900 | D8: 189000 | E8: users x conversion x $40-50 x 12%
A9: Agency subscriptions | B9: 4800 | C9: 25200 | D9: 58800 | E9: 8 / 35 / 70 agencies at $50-70 per month
A10: Agency B2B wholesale fee | B10: 1440 | C10: 16800 | D10: 58800 | E10: agencies x B2B volume x 12%
A11: Provider marketplace commission | B11: 2400 | C11: 21600 | D11: 75600 | E11: 50 / 200 / 450 providers
A12: eSIM / connectivity | B12: 6480 | C12: 64800 | D12: 151200 | E12: CONTINGENT — needs a telecom deal
A13: E-Mehmon compliance fee | B13: 0 | C13: 22500 | D13: 75000 | E13: CONTINGENT — needs the government agreement
A14: Sponsored placement | B14: 1200 | C14: 9000 | D14: 28000
A15: TOTAL REVENUE | B15: 22800 | C15: 232800 | D15: 636400
A16: revenue you control | B16: 16320 | C16: 145500 | D16: 410200 | E16: No third party required. This is the number to defend.
A17: contingent on partner / state | B17: 6480 | C17: 87300 | D17: 226200 | E17: Neither agreement is signed yet.
A18: COSTS
A19: Variable / COGS | B19: -3420 | C19: -34920 | D19: -89096 | E19: 15% / 15% / 14% of revenue
A20: Sales & marketing | B20: -5700 | C20: -46560 | D20: -114552 | E20: 25% / 20% / 18% of revenue
A21: Fixed (3 founders + tools) | B21: -38038 | C21: -29328 | D21: -29328 | E21: From SAFRON_Budget.xlsx
A22: Additional staff | B22: 0 | C22: -19200 | D22: -48000 | E22: 0 / 2 / 5 hires at $800 per month
A23: NET PROFIT / (LOSS) | B23: -24358 | C23: 102792 | D23: 355424
A24: Cumulative | B24: -24358 | C24: 78434 | D24: 433858 | E24: Break-even around month 15
A25: WHAT THE INVESTOR GETS ON $10,000
A26: His offer — 50% of revenue | B26: -11400 | C26: -116400 | D26: -318200 | E26: 3-year total to him: $446,000, and it never stops
A27: Counter — 7% capped at 2.0x | B27: -1596 | C27: -16296 | D27: -2108 | E27: 3-year total to him: $20,000, then it ends
A28: YOU keep under his offer | B28: -35758 | C28: -13608 | D28: 37224 | E28: Negative in years 1 and 2
A29: YOU keep under the counter | B29: -25954 | C29: 86496 | D29: 353316 | E29: The gap is what the structure is worth
A31: Market fact: 236 licensed tour operators nationally, ~186 in Tashkent city (official state registry, uzbekistan.travel).
A32: 70 paying agencies in Year 3 = 30% of the entire licensed market. Treat anything above that as optimistic.
A33: Net margin reaches 56% by Year 3. That is high for a marketplace — dial up Sales & marketing or Additional staff on the Assumptions sheet until it looks like a real company.

Sheet Assumptions
A1: Revenue Assumptions
A2: Blue = your input. Everything else calculates. Change any blue cell and the whole model moves.
A4: MARKET & ADOPTION | B4: Year 1 | C4: Year 2 | D4: Year 3 | E4: Basis
A5: Tourists per year | B5: 500000 | C5: 500000 | D5: 500000 | E5: Your figure. Note: national arrivals were 11.7M in 2025 — 500k is a narrower, more defensible "addressable foreign tourist" base.
A6: Share arriving in main season | B6: 0.9 | C6: 0.9 | D6: 0.9 | E6: Your figure: 450k of 500k.
A7: App adoption rate | B7: 0.05 | C7: 0.3 | D7: 0.5 | E7: Your plan: 5% / 30% / 50%.
A8: App users | B8: =B5*B6*B7 | C8: =C5*C6*C7 | D8: =D5*D6*D7 | E8: tourists x season share x adoption
A9: MARKETPLACE BOOKINGS | B9: Year 1 | C9: Year 2 | D9: Year 3 | E9: Basis
A10: Booking conversion of app users | B10: 0.06 | C10: 0.1 | D10: 0.14 | E10: Share of users who book at least once. Conservative: most travel apps convert 5-15%.
A11: Average booking value | B11: 40 | C11: 45 | D11: 50 | E11: Masterclass, yurt stay, guided experience. Typical rural experience pricing.
A12: Platform take rate | B12: 0.12 | C12: 0.12 | D12: 0.12 | E12: Midpoint of the 10-15% in your PRD.
A13: AGENCIES (B2B) | B13: Year 1 | C13: Year 2 | D13: Year 3 | E13: Basis
A14: Licensed tour operators nationally | B14: 236 | C14: 236 | D14: 236 | E14: REAL: official state registry, uzbekistan.travel. ~186 of these are Tashkent city.
A15: Paying agencies | B15: 8 | C15: 35 | D15: 70 | E15: Y3 = 30% of the entire licensed market. Above that is optimistic.
A16: Agency subscription / month | B16: 50 | C16: 60 | D16: 70 | E16: Local pricing. A Tashkent DMC will not pay US SaaS rates.
A17: B2B booking volume per agency / yr | B17: 1500 | C17: 4000 | D17: 7000 | E17: GMV each agency books through your provider inventory.
A18: PROVIDERS | B18: Year 1 | C18: Year 2 | D18: Year 3 | E18: Basis
A19: Onboarded providers | B19: 50 | C19: 200 | D19: 450 | E19: Deck slide 18 targets 50 in the pilot year.
A20: Avg bookings value per provider / yr | B20: 400 | C20: 900 | D20: 1400 | E20: Rural provider volume. Deliberately low.
A21: OTHER STREAMS | B21: Year 1 | C21: Year 2 | D21: Year 3 | E21: Basis
A22: eSIM attach rate | B22: 0.06 | C22: 0.1 | D22: 0.14 | E22: Share of app users buying a data plan.
A23: eSIM revenue per sale | B23: 12 | C23: 12 | D23: 12 | E23: Retail price.
A24: eSIM margin | B24: 0.4 | C24: 0.4 | D24: 0.4 | E24: Reseller margin.
A25: E-Mehmon registrations handled | B25: 0 | C25: 15000 | D25: 50000 | E25: Needs the government agreement. Zero in Y1 by design.
A26: Fee per registration | B26: 1.5 | C26: 1.5 | D26: 1.5 | E26: Blueprint proposes $1-2.
A27: Sponsored placement revenue | B27: 1200 | C27: 9000 | D27: 28000 | E27: Paid prominence for cafes and experiences.
A28: COSTS | B28: Year 1 | C28: Year 2 | D28: Year 3 | E28: Basis
A29: Fixed costs (from budget) | B29: 38038 | C29: 29328 | D29: 29328 | E29: From SAFRON_Budget.xlsx, buffered at 30%.
A30: Variable cost / COGS as % of revenue | B30: 0.15 | C30: 0.15 | D30: 0.14 | E30: Payment processing, cloud, first-line support.
A31: Sales & marketing as % of revenue | B31: 0.25 | C31: 0.2 | D31: 0.18 | E31: Acquiring 225k users and 70 agencies is not free. Investors expect to see this line.
A32: Additional staff beyond the 3 founders | B32: 0 | C32: 2 | D32: 5 | E32: You cannot serve 225,000 users and 70 agencies with three people.
A33: Cost per additional staff / year | B33: 9600 | C33: 9600 | D33: 9600 | E33: $800/mo. Below Tashkent IT market (~$1,450/mo) but above founder stipend.

Sheet Revenue
A1: Revenue Build
A3: Stream | B3: Year 1 | C3: Year 2 | D3: Year 3 | E3: How it is calculated
A4: Tourist booking commission | B4: =Assumptions!B8*Assumptions!B10*Assumptions!B11*Assumptions!B12 | C4: =Assumptions!C8*Assumptions!C10*Assumptions!C11*Assumptions!C12 | D4: =Assumptions!D8*Assumptions!D10*Assumptions!D11*Assumptions!D12 | E4: users x conversion x avg value x take rate
A5: Agency subscriptions | B5: =Assumptions!B15*Assumptions!B16*12 | C5: =Assumptions!C15*Assumptions!C16*12 | D5: =Assumptions!D15*Assumptions!D16*12 | E5: paying agencies x monthly price x 12
A6: Agency B2B wholesale fee | B6: =Assumptions!B15*Assumptions!B17*Assumptions!B12 | C6: =Assumptions!C15*Assumptions!C17*Assumptions!C12 | D6: =Assumptions!D15*Assumptions!D17*Assumptions!D12 | E6: agencies x B2B volume each x take rate
A7: Provider marketplace commission | B7: =Assumptions!B19*Assumptions!B20*Assumptions!B12 | C7: =Assumptions!C19*Assumptions!C20*Assumptions!C12 | D7: =Assumptions!D19*Assumptions!D20*Assumptions!D12 | E7: providers x annual bookings each x take rate
A8: eSIM / connectivity | B8: =Assumptions!B8*Assumptions!B22*Assumptions!B23*Assumptions!B24 | C8: =Assumptions!C8*Assumptions!C22*Assumptions!C23*Assumptions!C24 | D8: =Assumptions!D8*Assumptions!D22*Assumptions!D23*Assumptions!D24 | E8: CONTINGENT — needs a telecom reseller agreement.
A9: E-Mehmon compliance fee | B9: =Assumptions!B25*Assumptions!B26 | C9: =Assumptions!C25*Assumptions!C26 | D9: =Assumptions!D25*Assumptions!D26 | E9: CONTINGENT — needs the government agreement.
A10: Sponsored placement | B10: =Assumptions!B27 | C10: =Assumptions!C27 | D10: =Assumptions!D27 | E10: direct input
A11: TOTAL REVENUE | B11: =SUM(B4:B10) | C11: =SUM(C4:C10) | D11: =SUM(D4:D10)
A13: of which: revenue you control | B13: =SUM(B4:B7)+B10 | C13: =SUM(C4:C7)+C10 | D13: =SUM(D4:D7)+D10 | E13: Bookings, agency SaaS, B2B fees, provider commission, sponsorship. No third party required.
A14: of which: contingent on a partner or the state | B14: =B8+B9 | C14: =C8+C9 | D14: =D8+D9 | E14: eSIM needs a telecom deal; compliance needs the government agreement. Neither is signed.
A16: Revenue per app user | B16: =IFERROR(B11/Assumptions!B8,0) | C16: =IFERROR(C11/Assumptions!C8,0) | D16: =IFERROR(D11/Assumptions!D8,0) | E16: Sanity check. If this exceeds ~$5 the model is probably too optimistic.

Sheet P&L
A1: Profit & Loss and Payback
B3: Year 1 | C3: Year 2 | D3: Year 3 | E3: Note
A4: Revenue | B4: =Revenue!B11 | C4: =Revenue!C11 | D4: =Revenue!D11 | E4: From Revenue sheet.
A5: Variable costs | B5: =-Revenue!B11*Assumptions!B30 | C5: =-Revenue!C11*Assumptions!C30 | D5: =-Revenue!D11*Assumptions!D30 | E5: Payment processing, support, scaling.
A6: Sales & marketing | B6: =-Revenue!B11*Assumptions!B31 | C6: =-Revenue!C11*Assumptions!C31 | D6: =-Revenue!D11*Assumptions!D31 | E6: Scales with revenue.
A7: Fixed costs (3 founders + tools) | B7: =-Assumptions!B29 | C7: =-Assumptions!C29 | D7: =-Assumptions!D29 | E7: From SAFRON_Budget.xlsx.
A8: Additional staff | B8: =-Assumptions!B32*Assumptions!B33 | C8: =-Assumptions!C32*Assumptions!C33 | D8: =-Assumptions!D32*Assumptions!D33 | E8: Support, sales, ops as you scale.
A9: NET PROFIT / (LOSS) | B9: =B4+B5+B6+B7+B8 | C9: =C4+C5+C6+C7+C8 | D9: =D4+D5+D6+D7+D8
A11: Cumulative profit / (loss) | B11: =B9 | C11: =B10+C9 | D11: =C10+D9 | E11: Turning positive = you have paid back the raise.
A12: Net margin | B12: =IFERROR(B9/B4,0) | C12: =IFERROR(C9/C4,0) | D12: =IFERROR(D9/D4,0)
A14: INVESTOR RETURN ON $10,000
A15: Deal structure | B15: Y1 | C15: Y2 | D15: Y3 | E15: 3-year total to investor
A16: His offer: 50% of revenue, uncapped | B16: =B4*0.5 | C16: =C4*0.5 | D16: =D4*0.5 | E16: =SUM(B16:D16)
A17: Counter: 7% of revenue, capped at 2.0x | B17: =MIN(B4*0.07,20000) | C17: =MIN(C4*0.07,20000-B17) | D17: =MIN(D4*0.07,20000-B17-C17) | E17: =SUM(B17:D17)
A18: What you keep under his offer | B18: =B9-B16 | C18: =C9-C16 | D18: =D9-D16 | E18: Net profit minus his 50% of revenue.
A19: What you keep under the counter | B19: =B9-B17 | C19: =C9-C17 | D19: =D9-D17 | E19: The difference is what the structure is worth to you.
A21: Sanity note: if net margin exceeds ~30% in Year 3, the model is understating what it costs to grow. Dial up Sales & marketing or Additional staff until it looks like a real company.
